smartprint/__init__.py
smartprint-1.0.5.dist-info/LICENSE
smartprint-1.0.5.dist-info/METADATA
smartprint-1.0.5.dist-info/WHEEL
smartprint-1.0.5.dist-info/top_level.txt
smartprint-1.0.5.dist-info/RECORD
