Metadata-Version: 2.1
Name: smartprint
Version: 1.0.5
Summary: Include the variable name in print statements
Home-page: https://github.com/abcnishant007/smartprint
Author: abcnishant007
Author-email: abc.nishant007@gmail.com
Project-URL: Bug Tracker, https://github.com/abcnishant007/smartprint/issues
Classifier: Programming Language :: Python :: 3
Classifier: License :: OSI Approved :: MIT License
Classifier: Operating System :: OS Independent
Requires-Python: >=3.6
License-File: LICENSE
Requires-Dist: rich (==12.6.0)
